plone.app.layout-5.0.3-py3.13-nspkg.pth
plone/app/layout/__init__.py
plone/app/layout/configure.zcml
plone/app/layout/favicon_handler.py
plone/app/layout/permissions.zcml
plone/app/layout/testing.py
plone/app/layout/analytics/__init__.py
plone/app/layout/analytics/configure.zcml
plone/app/layout/analytics/view.pt
plone/app/layout/analytics/view.py
plone/app/layout/analytics/view_head.pt
plone/app/layout/analytics/tests/__init__.py
plone/app/layout/analytics/tests/analytics.txt
plone/app/layout/analytics/tests/test_doctests.py
plone/app/layout/globals/__init__.py
plone/app/layout/globals/configure.zcml
plone/app/layout/globals/context.py
plone/app/layout/globals/interface.py
plone/app/layout/globals/interfaces.py
plone/app/layout/globals/layout.py
plone/app/layout/globals/portal.py
plone/app/layout/globals/tools.py
plone/app/layout/globals/tests/__init__.py
plone/app/layout/globals/tests/test_context.py
plone/app/layout/globals/tests/test_interface.py
plone/app/layout/globals/tests/test_layout.py
plone/app/layout/globals/tests/test_portal.py
plone/app/layout/globals/tests/test_tools.py
plone/app/layout/globals/tests/data/bodyclass_nametest.pt
plone/app/layout/icons/__init__.py
plone/app/layout/icons/configure.zcml
plone/app/layout/icons/icons.py
plone/app/layout/icons/interfaces.py
plone/app/layout/links/__init__.py
plone/app/layout/links/author.pt
plone/app/layout/links/configure.zcml
plone/app/layout/links/favicon.pt
plone/app/layout/links/rsslink.pt
plone/app/layout/links/search.pt
plone/app/layout/links/viewlets.py
plone/app/layout/links/tests/__init__.py
plone/app/layout/links/tests/test_canonical_url.py
plone/app/layout/links/tests/test_favicon_viewlet.py
plone/app/layout/links/tests/test_rssviewlet.py
plone/app/layout/navigation/__init__.py
plone/app/layout/navigation/configure.zcml
plone/app/layout/navigation/interfaces.py
plone/app/layout/navigation/navtree.py
plone/app/layout/navigation/root.py
plone/app/layout/nextprevious/__init__.py
plone_app_layout-5.0.3.dist-info/METADATA
plone_app_layout-5.0.3.dist-info/WHEEL
plone_app_layout-5.0.3.dist-info/namespace_packages.txt
plone_app_layout-5.0.3.dist-info/top_level.txt
plone_app_layout-5.0.3.dist-info/RECORD
