Metadata-Version: 2.2
Name: plone.app.layout
Version: 5.0.3
Summary: Layout mechanisms for Plone
Home-page: https://pypi.org/project/plone.app.layout
Author: Plone Foundation
Author-email: plone-developers@lists.sourceforge.net
License: GPL version 2
Keywords: plone layout viewlet
Classifier: Development Status :: 6 - Mature
Classifier: Environment :: Web Environment
Classifier: Framework :: Plone
Classifier: Framework :: Plone :: 6.1
Classifier: Framework :: Plone :: Core
Classifier: Framework :: Zope :: 5
Classifier: License :: OSI Approved :: GNU General Public License v2 (GPLv2)
Classifier: Operating System :: OS Independent
Classifier: Programming Language :: Python
Classifier: Programming Language :: Python :: 3.10
Classifier: Programming Language :: Python :: 3.11
Classifier: Programming Language :: Python :: 3.12
Classifier: Programming Language :: Python :: 3.13
Requires-Python: >=3.10
Requires-Dist: plone.app.content
Requires-Dist: plone.app.dexterity
Requires-Dist: plone.app.relationfield
Requires-Dist: plone.app.uuid
Requires-Dist: plone.app.viewletmanager>=1.2
Requires-Dist: plone.base>=1.0.4
Requires-Dist: plone.dexterity
Requires-Dist: plone.formwidget.namedfile
Requires-Dist: plone.i18n
Requires-Dist: plone.memoize
Requires-Dist: plone.portlets
Requires-Dist: plone.protect
Requires-Dist: Products.CMFEditions>=1.2.2
Requires-Dist: Products.statusmessages
Requires-Dist: Products.ZCatalog
Requires-Dist: setuptools
Requires-Dist: Zope
Provides-Extra: test
Requires-Dist: plone.app.contenttypes[test]; extra == "test"
Requires-Dist: plone.app.relationfield; extra == "test"
Requires-Dist: plone.app.testing; extra == "test"
Requires-Dist: plone.dexterity; extra == "test"
Requires-Dist: plone.locking; extra == "test"
Requires-Dist: plone.testing; extra == "test"
Requires-Dist: z3c.relationfield; extra == "test"
Requires-Dist: zope.intid; extra == "test"
Dynamic: author
Dynamic: author-email
Dynamic: classifier
Dynamic: description
Dynamic: description-content-type
Dynamic: home-page
Dynamic: keywords
Dynamic: license
Dynamic: provides-extra
Dynamic: requires-dist
Dynamic: requires-python
Dynamic: summary
